capyutils/__init__.py
capyutils/context.py
capyutils/exceptions.py
capyutils/py.typed
capyutils/result.py
capyutils-0.1.8.dist-info/LICENSE
capyutils-0.1.8.dist-info/METADATA
capyutils-0.1.8.dist-info/WHEEL
capyutils-0.1.8.dist-info/RECORD
