Metadata-Version: 2.1
Name: capyutils
Version: 0.1.8
Summary: Collection of lightweight utils for diversified purposes
License: MIT
Author: carlosmspk
Author-email: carlosmspk@gmail.com
Requires-Python: >=3.8,<4.0
Classifier: License :: OSI Approved :: MIT License
Classifier: Programming Language :: Python :: 3
Classifier: Programming Language :: Python :: 3.8
Classifier: Programming Language :: Python :: 3.9
Classifier: Programming Language :: Python :: 3.10
Classifier: Programming Language :: Python :: 3.11
Classifier: Programming Language :: Python :: 3.12
